gryaml/__init__.py
gryaml/__main__.py
gryaml/_py2neo.py
gryaml/pyyaml.py
gryaml-1.0.0.dist-info/METADATA
gryaml-1.0.0.dist-info/RECORD
gryaml-1.0.0.dist-info/WHEEL
gryaml-1.0.0.dist-info/entry_points.txt
gryaml-1.0.0.dist-info/top_level.txt
