Metadata-Version: 2.1
Name: gryaml
Version: 1.0.0
Summary: Represent Neo4j graph data as YAML.
Home-page: https://github.com/wcooley/python-gryaml
Author: Wil Cooley
Author-email: wcooley@nakedape.cc
License: MIT
Keywords: yaml py2neo neo4j gryaml
Platform: UNKNOWN
Classifier: Development Status :: 2 - Pre-Alpha
Classifier: Intended Audience :: Developers
Classifier: License :: OSI Approved :: MIT License
Classifier: Natural Language :: English
Classifier: Programming Language :: Python :: 2
Classifier: Programming Language :: Python :: 2.7
Classifier: Programming Language :: Python :: 3
Classifier: Programming Language :: Python :: 3.4
Classifier: Programming Language :: Python :: 3.5
Classifier: Programming Language :: Python :: 3.6
Classifier: Programming Language :: Python :: Implementation :: PyPy
Provides-Extra: test
Requires-Dist: boltons
Requires-Dist: py2neo (<=2.999,>=1.6)
Requires-Dist: py2neo-compat (~=1.0.0pre0)
Requires-Dist: pyyaml
Provides-Extra: test
Requires-Dist: pytest; extra == 'test'
Requires-Dist: pytest-cov; extra == 'test'
Requires-Dist: pytest-forked; extra == 'test'
Provides-Extra: test
Requires-Dist: pathlib2; (python_version < "3") and extra == 'test'
